{
  "category": {
    "tag": "제조사",
    "Samsung": {
      "tag": "기종",
      "Galaxy S21 시리즈": {
        "tag": "세부 기종",
        "S21": {
          "pid": 13
        },
        "S21 Plus": {
          "pid": 14
        },
        "S21 Ultra": {
          "tag": "스토리지",
          "256G": {
            "pid": 15
          },
          "512G": {
            "pid": 16
          }
        }
      },
      "Galaxy S20 시리즈": {
        "tag": "세부 기종",
        "S20": {
          "pid": 8
        },
        "S20 Plus": {
          "pid": 9
        },
        "S20 Ultra": {
          "tag": "스토리지",
          "256G": {
            "pid": 10
          },
          "512G": {
            "pid": 11
          },
          "S20 FE": {
            "pid": 12
          }
        }
      },
      "Galaxy S10 시리즈": {
        "tag": "세부 기종",
        "S10e": {
          "pid": 1
        },
        "S10": {
          "tag": "스토리지",
          "128G": {
            "pid": 2
          },
          "512G": {
            "pid": 3
          }
        },
        "S10 Plus": {
          "tag": "스토리지",
          "256G": {
            "pid": 4
          },
          "512G": {
            "pid": 5
          }
        },
        "S10 5G": {
          "tag": "스토리지",
          "256G": {
            "pid": 6
          },
          "512G": {
            "pid": 7
          }
        }
      },
      "Galaxy Note20 시리즈": {
        "tag": "세부 기종",
        "Note20": {
          "pid": 34
        },
        "Note20 Ultra": {
          "pid": 35
        }
      },
      "Galaxy Note10 시리즈": {
        "tag":"세부 기종",
        "Note10": {
          "pid": 31
        },
        "note10 Plus": {
          "tag": "스토리지",
          "256G": {
            "pid": 32
          },
          "512G": {
            "pid": 33
          }
        }
      },
      "Galaxy Z Flip 3": {
        "pid": 57
      },
      "Galaxy Z Fold 3": {
        "tag": "스토리지",
        "256G": {
          "pid": 55
        },
        "512G": {
          "pid": 56
        }
      },
      "Galaxy Z Fold 2": {
        "tag": "스토리지",
        "256G": {
          "pid": 53
        },
        "512G": {
          "pid": 54
        }
      },
      "Galaxy Fold 1": {
        "pid": 51
      }
    },
    "Apple": {
      "tag": "기종",
      "iPhone 11 시리즈": {
        "tag": "세부 기종",
        "iPhone 11": {
          "tag": "스토리지",
          "64G": {
            "pid": 86
          },
          "128G": {
            "pid": 87
          },
          "256G": {
            "pid": 88
          }
        },
        "iPhone 11 Pro": {
          "tag": "스토리지",
          "64G": {
            "pid": 89
          },
          "256G": {
            "pid": 90
          },
          "512G": {
            "pid": 91
          }
        },
        "iPhone 11 Pro Max": {
          "tag": "스토리지",
          "64G": {
            "pid": 92
          },
          "256G": {
            "pid": 93
          },
          "512G": {
            "pid": 94
          }
        }
      },
      "iPhone X 시리즈": {
        "tag":"세부 기종",
        "iPhone X": {
          "tag": "스토리지",
          "64G": {
            "pid": 70
          },
          "256G": {
            "pid": 71
          }
        },
        "iPhone XS": {
          "tag": "스토리지",
          "64G": {
            "pid": 72
          },
          "256G": {
            "pid": 73
          },
          "512G": {
            "pid": 74
          }
        },
        "iPhone XS Max": {
          "tag": "스토리지",
          "64G": {
            "pid": 75
          },
          "256G": {
            "pid": 76
          },
          "512G": {
            "pid": 77
          }
        },
        "iPhone XR": {
          "tag": "스토리지",
          "64G": {
            "pid": 78
          },
          "128G": {
            "pid": 79
          },
          "256G": {
            "pid": 80
          }
        }
      },
      "iPhone SE2": {
        "tag": "스토리지",
        "64G": {
          "pid": 95
        },
        "128G": {
          "pid": 96
        }
      }
    }
  }
}
